deformation/__init__.py
deformation/affine.py
deformation/core.py
deformation/doc.py
deformation/metadata.py
deformation/padding.py
deformation/perspective.py
deformation/poly.py
deformation/rotation.py
deformation/test.py
deformation-1.0.7.dist-info/LICENSE
deformation-1.0.7.dist-info/METADATA
deformation-1.0.7.dist-info/WHEEL
deformation-1.0.7.dist-info/top_level.txt
deformation-1.0.7.dist-info/RECORD
