Metadata-Version: 2.1
Name: deformation
Version: 1.0.7
Summary: Chain image distortion.
Home-page: https://framagit.org/robinechuca/deformation/-/blob/main/README.rst
Author: Robin RICHARD (robinechuca) <serveurpython.oz@gmail.com>
Author-email: serveurpython.oz@gmail.com
Project-URL: Source Repository, https://framagit.org/robinechuca/deformation
Project-URL: Documentation, http://python-docs.ddns.net/deformation/
Keywords: image,dewarping,warpingwarp,deformation,distortion
Classifier: Development Status :: 4 - Beta
Classifier: Natural Language :: English
Classifier: Operating System :: OS Independent
Classifier: Programming Language :: Python :: 3.6
Classifier: Programming Language :: Python :: 3.7
Classifier: Programming Language :: Python :: 3.8
Classifier: Programming Language :: Python :: 3.9
Classifier: Programming Language :: Python :: 3.10
Classifier: Topic :: Multimedia :: Graphics
Classifier: Topic :: Scientific/Engineering :: Image Processing
Requires-Python: >=3.6
License-File: LICENSE
Requires-Dist: numpy
Requires-Dist: opencv-python
Requires-Dist: sympy
Requires-Dist: torch
Provides-Extra: dev
Requires-Dist: pytest ; extra == 'dev'
Requires-Dist: pylint ; extra == 'dev'
Requires-Dist: pdoc3 ; extra == 'dev'
Requires-Dist: pyreverse ; extra == 'dev'
Requires-Dist: context-verbose ; extra == 'dev'
Requires-Dist: matplotlib ; extra == 'dev'
